[
    {
        "url": "",
        "id": "1",
        "isFavorite": false
    },
    {
        "url": "",
        "id": "2",
        "isFavorite": false
    },
    {
        "url": "",
        "id": "3",
        "isFavorite": false
    },
    {
        "url": "",
        "id": "4",
        "isFavorite": false
    },
    {
        "url": "",
        "id": "5",
        "isFavorite": false
    },
    {
        "url": "",
        "id": "6",
        "isFavorite": false
    },
    {
        "url": "",
        "id": "7",
        "isFavorite": false
    },
    {
        "url": "",
        "id": "8",
        "isFavorite": false
    },
    {
        "url": "",
        "id": "9",
        "isFavorite": false
    },
    {
        "url": "",
        "id": "10",
        "isFavorite": false
    },
    {
        "url": "",
        "id": "11",
        "isFavorite": false
    },
    {
        "url": "",
        "id": "12",
        "isFavorite": false
    },
    {
        "url": "",
        "id": "13",
        "isFavorite": false
    },
    {
        "url": "",
        "id": "14",
        "isFavorite": false
    },
    {
        "url": "",
        "id": "15",
        "isFavorite": false
    },
    {
        "url": "",
        "id": "16",
        "isFavorite": false
    },
    {
        "url": "",
        "id": "17",
        "isFavorite": false
    },
    {
        "url": "",
        "id": "18",
        "isFavorite": false
    },
    {
        "url": "",
        "id": "19",
        "isFavorite": false
    },
    {
        "url": "",
        "id": "20",
        "isFavorite": false
    },
    {
        "url": "",
        "id": "21",
        "isFavorite": false
    },
    {
        "url": "",
        "id": "22",
        "isFavorite": false
    },
    {
        "url": "",
        "id": "23",
        "isFavorite": false
    }
]